prowler/__init__.py
prowler/__main__.py
prowler/compliance/aws/__init__.py
prowler/compliance/aws/aws_audit_manager_control_tower_guardrails_aws.json
prowler/compliance/aws/aws_foundational_security_best_practices_aws.json
prowler/compliance/aws/cis_1.4_aws.json
prowler/compliance/aws/cis_1.5_aws.json
prowler/compliance/aws/cisa_aws.json
prowler/compliance/aws/ens_rd2022_aws.json
prowler/compliance/aws/fedramp_low_revision_4_aws.json
prowler/compliance/aws/fedramp_moderate_revision_4_aws.json
prowler/compliance/aws/ffiec_aws.json
prowler/compliance/aws/gdpr_aws.json
prowler/compliance/aws/gxp_21_cfr_part_11_aws.json
prowler/compliance/aws/gxp_eu_annex_11_aws.json
prowler/compliance/aws/hipaa_aws.json
prowler/compliance/aws/nist_800_171_revision_2_aws.json
prowler/compliance/aws/nist_800_53_revision_4_aws.json
prowler/compliance/aws/nist_800_53_revision_5_aws.json
prowler/compliance/aws/nist_csf_1.1_aws.json
prowler/compliance/aws/pci_3.2.1_aws.json
prowler/compliance/aws/rbi_cyber_security_framework_aws.json
prowler/compliance/aws/soc2_aws.json
prowler/compliance/azure/__init__.py
prowler/config/__init__.py
prowler/config/allowlist.yaml
prowler/config/checklist_example.json
prowler/config/config.py
prowler/config/config.yaml
prowler/lib/__init__.py
prowler/lib/banner.py
prowler/lib/check/__init__.py
prowler/lib/check/check.py
prowler/lib/check/checks_loader.py
prowler/lib/check/compliance.py
prowler/lib/check/compliance_models.py
prowler/lib/check/models.py
prowler/lib/cli/__init__.py
prowler/lib/cli/parser.py
prowler/lib/logger.py
prowler/lib/outputs/__init__.py
prowler/lib/outputs/compliance.py
prowler/lib/outputs/file_descriptors.py
prowler/lib/outputs/html.py
prowler/lib/outputs/json.py
prowler/lib/outputs/models.py
prowler/lib/outputs/outputs.py
prowler/lib/outputs/summary_table.py
prowler/lib/scan_filters/__init__.py
prowler/lib/scan_filters/scan_filters.py
prowler/lib/utils/__init__.py
prowler/lib/utils/utils.py
prowler/providers/aws/__init__.py
prowler_cloud-3.3.4.dist-info/LICENSE
prowler_cloud-3.3.4.dist-info/WHEEL
prowler_cloud-3.3.4.dist-info/entry_points.txt
prowler_cloud-3.3.4.dist-info/METADATA
prowler_cloud-3.3.4.dist-info/RECORD
